s3pipeline/__init__.py
s3pipeline/items.py
s3pipeline/pipelines.py
s3pipeline/strategies/__init__.py
s3pipeline/strategies/error.py
s3pipeline/strategies/gcs.py
s3pipeline/strategies/s3.py
scrapy_s3pipeline-0.7.0.dist-info/LICENSE
scrapy_s3pipeline-0.7.0.dist-info/METADATA
scrapy_s3pipeline-0.7.0.dist-info/WHEEL
scrapy_s3pipeline-0.7.0.dist-info/top_level.txt
scrapy_s3pipeline-0.7.0.dist-info/RECORD
