Metadata-Version: 2.1
Name: scrapy-s3pipeline
Version: 0.7.0
Summary: Scrapy pipeline to store chunked items into Amazon S3 or Google Clous Storage bucket
Home-page: https://github.com/orangain/scrapy-s3pipeline
Author: orangain
Author-email: orangain@gmail.com
License: MIT
Keywords: scrapy pipeline aws s3 gcs serverless
Platform: UNKNOWN
Classifier: Development Status :: 4 - Beta
Classifier: License :: OSI Approved :: MIT License
Classifier: Programming Language :: Python :: 3
Classifier: Programming Language :: Python :: 3.6
Classifier: Programming Language :: Python :: 3.7
Classifier: Programming Language :: Python :: 3.8
Classifier: Programming Language :: Python :: 3.9
Classifier: Framework :: Scrapy
Requires-Dist: Scrapy (>=1.1)
Provides-Extra: gcs
Requires-Dist: google-cloud-storage ; extra == 'gcs'
Provides-Extra: s3
Requires-Dist: boto3 ; extra == 's3'
